stix_shifter_utils/__init__.py
stix_shifter_utils/modules/__init__.py
stix_shifter_utils/modules/base/__init__.py
stix_shifter_utils/modules/base/stix_translation/__init__.py
stix_shifter_utils/modules/base/stix_translation/base_query_translator.py
stix_shifter_utils/modules/base/stix_translation/base_results_translator.py
stix_shifter_utils/modules/base/stix_translation/empty_query_translator.py
stix_shifter_utils/modules/base/stix_transmission/__init__.py
stix_shifter_utils/modules/base/stix_transmission/base_connector.py
stix_shifter_utils/modules/base/stix_transmission/base_delete_connector.py
stix_shifter_utils/modules/base/stix_transmission/base_json_connector.py
stix_shifter_utils/modules/base/stix_transmission/base_json_results_connector.py
stix_shifter_utils/modules/base/stix_transmission/base_json_sync_connector.py
stix_shifter_utils/modules/base/stix_transmission/base_ping_connector.py
stix_shifter_utils/modules/base/stix_transmission/base_query_connector.py
stix_shifter_utils/modules/base/stix_transmission/base_results_connector.py
stix_shifter_utils/modules/base/stix_transmission/base_status_connector.py
stix_shifter_utils/modules/base/stix_transmission/base_sync_connector.py
stix_shifter_utils/modules/car/__init__.py
stix_shifter_utils/modules/car/stix_translation/__init__.py
stix_shifter_utils/modules/car/stix_translation/query_translator.py
stix_shifter_utils/modules/car/stix_translation/results_translator.py
stix_shifter_utils/modules/car/stix_translation/json/car_from_stix_map.json
stix_shifter_utils/modules/car/stix_translation/json/to_stix_map.json
stix_shifter_utils/modules/cim/__init__.py
stix_shifter_utils/modules/cim/stix_translation/__init__.py
stix_shifter_utils/modules/cim/stix_translation/query_translator.py
stix_shifter_utils/modules/cim/stix_translation/json/cim_from_stix_map.json
stix_shifter_utils/modules/cim/stix_translation/json/cim_select_fields.json
stix_shifter_utils/normalization/BaseNormalization.py
stix_shifter_utils-8.0.2.dist-info/licenses/AUTHORS.md
stix_shifter_utils-8.0.2.dist-info/licenses/LICENSE.md
stix_shifter_utils-8.0.2.dist-info/licenses/NOTICE
stix_shifter_utils-8.0.2.dist-info/METADATA
stix_shifter_utils-8.0.2.dist-info/WHEEL
stix_shifter_utils-8.0.2.dist-info/top_level.txt
stix_shifter_utils-8.0.2.dist-info/RECORD
